oceantracker/__init__.py
oceantracker/definitions.py
oceantracker/main.py
oceantracker/oceantracker_params_runner.py
oceantracker/run_ot_cmd_line.py
oceantracker/shared_info.py
oceantracker/dispersion/__init__.py
oceantracker/dispersion/_base_dispersion.py
oceantracker/dispersion/random_walk.py
oceantracker/event_loggers/__init__.py
oceantracker/event_loggers/_base_event_loggers.py
oceantracker/event_loggers/log_polygon_entry_and_exit.py
oceantracker/field_group_manager/__init__.py
oceantracker/field_group_manager/dev_nested_grids_field_group_manager.py
oceantracker/field_group_manager/field_group_manager.py
oceantracker/field_group_manager/setup_reader.py
oceantracker/field_group_manager/dev/__init__.py
oceantracker/field_group_manager/dev/_dev_parallel_reader.py
oceantracker/field_group_manager/util/__init__.py
oceantracker/field_group_manager/util/field_group_manager_util.py
oceantracker/fields/__init__.py
oceantracker/fields/_base_field.py
oceantracker/fields/field_vertical_gradient.py
oceantracker/fields/friction_velocity.py
oceantracker/fields/reader_field.py
oceantracker/fields/total_water_depth.py
oceantracker/fields/util/__init__.py
oceantracker/integrated_model/__init__.py
oceantracker/integrated_model/_base_model.py
oceantracker/integrated_model/lagraingian_structures_FTLE_2D.py
oceantracker/interpolator/__init__.py
oceantracker/interpolator/_base_interp.py
oceantracker/interpolator/_eval_interp_triangles.py
oceantracker/interpolator/_find_hori_cell_triangle_walk.py
oceantracker/interpolator/_find_vertical_cell_classes.py
oceantracker/interpolator/interp_triangle_native_grid.py
oceantracker/interpolator/depricated/__init__.py
oceantracker/interpolator/dev/__init__.py
oceantracker/interpolator/util/__init__.py
oceantracker/interpolator/util/find_initial_cell.py
oceantracker/interpolator/util/interp_kernals.py
oceantracker/interpolator/util/triangle_eval_interp.py
oceantracker/interpolator/util/triangle_interpolator_util.py
oceantracker-0.5.3.0.dist-info/licenses/LICENSE.md
oceantracker-0.5.3.0.dist-info/METADATA
oceantracker-0.5.3.0.dist-info/WHEEL
oceantracker-0.5.3.0.dist-info/entry_points.txt
oceantracker-0.5.3.0.dist-info/top_level.txt
oceantracker-0.5.3.0.dist-info/RECORD
