Metadata-Version: 2.4
Name: oceantracker
Version: 0.5.3.0
Summary: Fast offline Lagrangian particle tracking in the Ocean for structured and unstructured grids
Author-email: Ross Vennell <ross.vennell@cawthron.org.nz>, Laurin Steidle <laurin.steidle@cawthron.org.nz>
Maintainer-email: Ross Vennell <ross.vennell@cawthron.org.nz>, Laurin Steidle <laurin.steidle@cawthron.org.nz>
License-Expression: MIT
Project-URL: Homepage, https://oceantracker.github.io/oceantracker/
Project-URL: Documentation, https://oceantracker.github.io/oceantracker/
Project-URL: Repository, https://github.com/oceantracker/oceantracker
Project-URL: Issues, https://github.com/oceantracker/oceantracker/issues
Keywords: oceanography,particle tracking,lagrangian,ocean modeling
Classifier: Development Status :: 4 - Beta
Classifier: Intended Audience :: Science/Research
Classifier: Operating System :: OS Independent
Classifier: Programming Language :: Python :: 3
Classifier: Programming Language :: Python :: 3.10
Classifier: Programming Language :: Python :: 3.11
Classifier: Programming Language :: Python :: 3.12
Classifier: Programming Language :: Python :: 3.13
Classifier: Topic :: Scientific/Engineering :: Physics
Classifier: Topic :: Scientific/Engineering :: Oceanography
Requires-Python: >=3.10
License-File: LICENSE.md
Requires-Dist: numba
Requires-Dist: numpy
Requires-Dist: netcdf4
Requires-Dist: xarray
Requires-Dist: scipy
Requires-Dist: pyproj
Requires-Dist: psutil
Requires-Dist: matplotlib
Requires-Dist: pyyaml
Requires-Dist: ffmpeg-python
Requires-Dist: ipykernel
Requires-Dist: requests
Provides-Extra: dev
Requires-Dist: build; extra == "dev"
Requires-Dist: twine; extra == "dev"
Requires-Dist: sphinx<9.0,>=7.0; extra == "dev"
Requires-Dist: sphinx-toolbox>=3.3.0; extra == "dev"
Requires-Dist: sphinxawesome-theme; extra == "dev"
Requires-Dist: sphinx-design; extra == "dev"
Requires-Dist: nbsphinx; extra == "dev"
Requires-Dist: ipython; extra == "dev"
Requires-Dist: rst2pdf; extra == "dev"
Requires-Dist: pytest>=7.0; extra == "dev"
Requires-Dist: pytest-xdist; extra == "dev"
Requires-Dist: coverage; extra == "dev"
Requires-Dist: pytest-cov; extra == "dev"
Requires-Dist: jupyter; extra == "dev"
Requires-Dist: nbclient; extra == "dev"
Requires-Dist: ffmpeg; extra == "dev"
Dynamic: license-file
